LICENSE
README.md
setup.py
src/contracting/__init__.py
src/contracting/client.py
src/contracting/constants.py
src/contracting/compilation/__init__.py
src/contracting/compilation/compiler.py
src/contracting/compilation/linter.py
src/contracting/compilation/parser.py
src/contracting/compilation/whitelists.py
src/contracting/contracts/__init__.py
src/contracting/contracts/submission.s.py
src/contracting/execution/__init__.py
src/contracting/execution/executor.py
src/contracting/execution/module.py
src/contracting/execution/runtime.py
src/contracting/execution/metering/__init__.py
src/contracting/execution/metering/tracer.c
src/contracting/stdlib/__init__.py
src/contracting/stdlib/env.py
src/contracting/stdlib/bridge/__init__.py
src/contracting/stdlib/bridge/access.py
src/contracting/stdlib/bridge/crypto.py
src/contracting/stdlib/bridge/decimal.py
src/contracting/stdlib/bridge/hashing.py
src/contracting/stdlib/bridge/imports.py
src/contracting/stdlib/bridge/orm.py
src/contracting/stdlib/bridge/random.py
src/contracting/stdlib/bridge/time.py
src/contracting/storage/__init__.py
src/contracting/storage/contract.py
src/contracting/storage/driver.py
src/contracting/storage/encoder.py
src/contracting/storage/hdf5.py
src/contracting/storage/orm.py
src/xian_contracting_py311.egg-info/PKG-INFO
src/xian_contracting_py311.egg-info/SOURCES.txt
src/xian_contracting_py311.egg-info/dependency_links.txt
src/xian_contracting_py311.egg-info/requires.txt
src/xian_contracting_py311.egg-info/top_level.txt
src/xian_contracting_py311.egg-info/zip-safe